minesweepervariants/__init__.py
minesweepervariants/__main__.py
minesweepervariants/abs/Lrule.py
minesweepervariants/abs/Mrule.py
minesweepervariants/abs/Rrule.py
minesweepervariants/abs/__init__.py
minesweepervariants/abs/board.py
minesweepervariants/abs/rule.py
minesweepervariants/assets/CopperplateCC-Heavy.ttf
minesweepervariants/assets/Cross_black.png
minesweepervariants/assets/Flag.png
minesweepervariants/assets/Flag_black.png
minesweepervariants/assets/arrow.svg
minesweepervariants/assets/circle.png
minesweepervariants/assets/circle.svg
minesweepervariants/assets/circle_black.png
minesweepervariants/assets/cross.png
minesweepervariants/assets/cross.svg
minesweepervariants/assets/double_arrow.svg
minesweepervariants/assets/double_horizontal_arrow.png
minesweepervariants/assets/double_horizontal_arrow_black.png
minesweepervariants/assets/double_vertical_arrow.png
minesweepervariants/assets/double_vertical_arrow_black.png
minesweepervariants/assets/down.png
minesweepervariants/assets/down_black.png
minesweepervariants/assets/down_flag.png
minesweepervariants/assets/flag.svg
minesweepervariants/assets/left.png
minesweepervariants/assets/left_black.png
minesweepervariants/assets/left_flag.png
minesweepervariants/assets/msyh_boot.ttf
minesweepervariants/assets/right.png
minesweepervariants/assets/right_black.png
minesweepervariants/assets/right_flag.png
minesweepervariants/assets/sqrt.png
minesweepervariants/assets/sqrt_black.png
minesweepervariants/assets/star.svg
minesweepervariants/assets/up.png
minesweepervariants/assets/up_black.png
minesweepervariants/assets/up_flag.png
minesweepervariants/config/base_image_config.yaml
minesweepervariants/config/base_puzzle_config.yaml
minesweepervariants/config/config.py
minesweepervariants/config/default.yaml
minesweepervariants/doc/README.md
minesweepervariants/doc/dev/board_api.md
minesweepervariants/doc/dev/rule_clue.md
minesweepervariants/doc/dev/rule_clue_mines.md
minesweepervariants/doc/dev/rule_mines.md
minesweepervariants-1.1.2.dist-info/LICENSE
minesweepervariants-1.1.2.dist-info/METADATA
minesweepervariants-1.1.2.dist-info/WHEEL
minesweepervariants-1.1.2.dist-info/RECORD
