Metadata-Version: 2.3
Name: minesweepervariants
Version: 1.1.2
Summary: 
License: GPL-3.0-or-later
Author: Minesweepervariants-Fanmade(Organization)
Author-email: Minesweepervariants-Fanmade@outlook.com
Requires-Python: >=3.12,<3.15
Classifier: License :: OSI Approved :: GNU General Public License v3 or later (GPLv3+)
Classifier: Programming Language :: Python :: 3
Classifier: Programming Language :: Python :: 3.12
Classifier: Programming Language :: Python :: 3.13
Provides-Extra: image
Provides-Extra: server
Requires-Dist: flask-cors (>=6.0.1,<7.0.0) ; extra == "server"
Requires-Dist: flask[async] (>=3.1.2,<4.0.0) ; extra == "server"
Requires-Dist: orjson (>=3.11.2,<4.0.0) ; extra == "server"
Requires-Dist: ortools (>=9.13.4784,<9.14.0)
Requires-Dist: pillow (>=11.3.0,<11.4.0) ; extra == "image"
Requires-Dist: requests (>=2.28.0,<3.0.0) ; extra == "server"
Requires-Dist: waitress (>=3.0.2,<3.1.0) ; extra == "server"
